{
    "dealer": 1,
    "dora": [
        "back",
        "back",
        "Tiao2",
        "back",
        "back"
    ],
    "players": {
        "1": {
            "hand": [
                "Wan8",
                "Wan6",
                "Feng_E",
                "Feng_E",
                "Wan6",
                "Wan9",
                "Wan7",
                "Wan1",
                "Feng_N",
                "Feng_N"
            ],
            "discarded": [
                "Tiao6",
                "SanYuan_W",
                "Tong2",
                "Tong4",
                "Feng_S",
                "SanYuan_R",
                "Feng_S",
                "Tiao7",
                "Tong1",
                "Feng_W"
            ],
            "melds": [
                "SanYuan_G",
                "SanYuan_G",
                "SanYuan_G"
            ],
            "riichi": false,
            "action_indicator": "thinking"
        },
        "2": {
            "discarded": [
                "Tong6",
                "Tiao5",
                "Tiao2",
                "Tiao5_R",
                "Wan8",
                "Tong7",
                "Tong9",
                "Tiao1",
                "Tong2",
                "Feng_S",
                "Wan1",
                "Tiao9",
                "Wan2"
            ],
            "melds": [
                "Tiao6",
                "Tiao8",
                "Tiao7",
                "Tong4",
                "Tong2",
                "Tong3"
            ],
            "riichi": false,
            "action_indicator": "thinking"
        },
        "3": {
            "discarded": [
                "Tong3",
                "Tiao1",
                "Tiao1",
                "Tong7",
                "SanYuan_R",
                "Tiao4",
                "Tiao9",
                "Tong2",
                "SanYuan_R",
                "Feng_W",
                "Feng_W",
                "Wan1"
            ],
            "melds": [],
            "riichi": false,
            "action_indicator": "thinking"
        },
        "4": {
            "discarded": [
                "SanYuan_W",
                "Wan8",
                "Wan1",
                "Tiao8",
                "Tong9",
                "SanYuan_R",
                "Tong9",
                "Wan9",
                "Tong1",
                "Tiao1",
                "Feng_S",
                "Wan8"
            ],
            "melds": [],
            "riichi": false,
            "action_indicator": "thinking"
        }
    }
}